Metadata-Version: 2.4
Name: deepcode-hku
Version: 1.0.7
Summary: AI Research Engine - Transform research papers into working code automatically
Home-page: https://github.com/HKUDS/DeepCode
Author: DeepCodeTeam
Project-URL: Documentation, https://github.com/HKUDS/DeepCode
Project-URL: Source, https://github.com/HKUDS/DeepCode
Project-URL: Tracker, https://github.com/HKUDS/DeepCode/issues
Classifier: Development Status :: 4 - Beta
Classifier: Programming Language :: Python :: 3
Classifier: License :: OSI Approved :: MIT License
Classifier: Operating System :: OS Independent
Classifier: Intended Audience :: Developers
Classifier: Intended Audience :: Science/Research
Classifier: Topic :: Software Development :: Libraries :: Python Modules
Classifier: Topic :: Scientific/Engineering :: Artificial Intelligence
Classifier: Topic :: Text Processing :: Linguistic
Requires-Python: >=3.9
License-File: LICENSE
Requires-Dist: aiofiles>=0.8.0
Requires-Dist: aiohttp>=3.8.0
Requires-Dist: anthropic
Requires-Dist: asyncio-mqtt
Requires-Dist: docling
Requires-Dist: mcp-agent
Requires-Dist: mcp-server-git
Requires-Dist: nest_asyncio
Requires-Dist: openai
Requires-Dist: pathlib2
Requires-Dist: PyPDF2>=2.0.0
Requires-Dist: reportlab>=3.5.0
Requires-Dist: streamlit
Dynamic: author
Dynamic: classifier
Dynamic: description
Dynamic: description-content-type
Dynamic: home-page
Dynamic: license-file
Dynamic: project-url
Dynamic: requires-dist
Dynamic: requires-python
Dynamic: summary
